Flask_CAS_fork-1.0.1.dist-info/DESCRIPTION.rst
Flask_CAS_fork-1.0.1.dist-info/METADATA
Flask_CAS_fork-1.0.1.dist-info/RECORD
Flask_CAS_fork-1.0.1.dist-info/WHEEL
Flask_CAS_fork-1.0.1.dist-info/metadata.json
Flask_CAS_fork-1.0.1.dist-info/top_level.txt
flask_cas/__init__.py
flask_cas/cas_urls.py
flask_cas/routing.py
