Metadata-Version: 2.0
Name: Flask-CAS-fork
Version: 1.0.1
Summary: Flask extension for CAS
Home-page: https://github.com/wgwz/Flask-CAS
Author: Cameron Brandon White
Author-email: cameronbwhite90@gmail.com
License: UNKNOWN
Platform: UNKNOWN
Classifier: Environment :: Web Environment
Classifier: Intended Audience :: Developers
Classifier: License :: OSI Approved :: BSD License
Classifier: Operating System :: OS Independent
Classifier: Programming Language :: Python
Classifier: Topic :: Internet :: WWW/HTTP :: Dynamic Content
Classifier: Topic :: Software Development :: Libraries :: Python Modules
Requires-Dist: Flask
Requires-Dist: xmltodict
